MANIFEST.in
README.txt
setup.py
lfs_order_numbers/__init__.py
lfs_order_numbers/models.py
lfs_order_numbers/tests.py
lfs_order_numbers.egg-info/PKG-INFO
lfs_order_numbers.egg-info/SOURCES.txt
lfs_order_numbers.egg-info/dependency_links.txt
lfs_order_numbers.egg-info/not-zip-safe
lfs_order_numbers.egg-info/requires.txt
lfs_order_numbers.egg-info/top_level.txt
lfs_order_numbers/migrations/0001_initial.py
lfs_order_numbers/migrations/__init__.py